README.rst
setup.cfg
setup.py
mapchete_safe/__init__.py
mapchete_safe.egg-info/PKG-INFO
mapchete_safe.egg-info/SOURCES.txt
mapchete_safe.egg-info/dependency_links.txt
mapchete_safe.egg-info/entry_points.txt
mapchete_safe.egg-info/requires.txt
mapchete_safe.egg-info/top_level.txt
test/test_module.py