Metadata-Version: 1.1
Name: mapchete-safe
Version: 0.7
Summary: Mapchete SAFE file read extension
Home-page: https://github.com/ungarj/mapchete-safe
Author: Joachim Ungar
Author-email: joachim.ungar@eox.at
License: MIT
Platform: UNKNOWN
Classifier: Development Status :: 3 - Alpha
Classifier: Intended Audience :: Developers
Classifier: Topic :: Scientific/Engineering :: GIS
Classifier: License :: OSI Approved :: MIT License
Classifier: Programming Language :: Python :: 2.7
